fastapi_tasks/__init__.py
fastapi_tasks/dependencies.py
fastapi_tasks/errors.py
fastapi_tasks/py.typed
fastapi_tasks/tasks.py
fastapi_tasks/utils.py
fastapi_tasks-0.1.0.dist-info/METADATA
fastapi_tasks-0.1.0.dist-info/WHEEL
fastapi_tasks-0.1.0.dist-info/licenses/LICENSE
fastapi_tasks-0.1.0.dist-info/RECORD
