Metadata-Version: 2.4
Name: fastapi-tasks
Version: 0.1.0
Summary: A simple task queue for FastAPI applications.
Project-URL: Repository, https://github.com/uriyyo/fastapi-tasks
Author-email: Yurii Karabas <1998uriyyo@gmail.com>
License-Expression: MIT
License-File: LICENSE
Classifier: Operating System :: OS Independent
Classifier: Programming Language :: Python
Classifier: Programming Language :: Python :: 3
Classifier: Programming Language :: Python :: 3 :: Only
Classifier: Programming Language :: Python :: 3.10
Classifier: Programming Language :: Python :: 3.11
Classifier: Programming Language :: Python :: 3.12
Classifier: Programming Language :: Python :: 3.13
Classifier: Programming Language :: Python :: 3.14
Requires-Python: >=3.10
Requires-Dist: fastapi>=0.128.0
